javscraper/__init__.py
javscraper/aircontrol.py
javscraper/alicejapan.py
javscraper/aroma.py
javscraper/attackers.py
javscraper/auroraproject.py
javscraper/base.py
javscraper/befree.py
javscraper/bi.py
javscraper/bigmorkal.py
javscraper/caribbeancom.py
javscraper/deeps.py
javscraper/dmm.py
javscraper/heyzo.py
javscraper/ideapocket.py
javscraper/javlibrary.py
javscraper/kmproduce.py
javscraper/maxa.py
javscraper/mgstage.py
javscraper/onepondo.py
javscraper/r18.py
javscraper/s1.py
javscraper/sod.py
javscraper/tenmusume.py
javscraper/utils.py
javscraper-1.1.8.dist-info/COPYING
javscraper-1.1.8.dist-info/METADATA
javscraper-1.1.8.dist-info/WHEEL
javscraper-1.1.8.dist-info/top_level.txt
javscraper-1.1.8.dist-info/RECORD
